Metadata-Version: 2.4
Name: pygnome
Version: 0.3.0
Summary: Python library for genome annotations
Author: PyGnome Team
License: MIT
Project-URL: Homepage, https://github.com/pcingola/pygnome
Project-URL: Bug Tracker, https://github.com/pcingola/pygnome/issues
Classifier: Development Status :: 3 - Alpha
Classifier: Intended Audience :: Science/Research
Classifier: License :: OSI Approved :: MIT License
Classifier: Programming Language :: Python :: 3
Classifier: Programming Language :: Python :: 3.10
Classifier: Topic :: Scientific/Engineering :: Bio-Informatics
Requires-Python: >=3.10
License-File: LICENSE
Requires-Dist: ipykernel>=6.29.5
Requires-Dist: numpy>=2.2.5
Provides-Extra: docs
Requires-Dist: mkdocs>=1.4.0; extra == "docs"
Requires-Dist: mkdocs-material>=9.0.0; extra == "docs"
Requires-Dist: mkdocstrings[python]>=0.20.0; extra == "docs"
Requires-Dist: mkdocs-gen-files>=0.5.0; extra == "docs"
Requires-Dist: mkdocs-literate-nav>=0.6.0; extra == "docs"
Dynamic: license-file
